[
 {
  "title": "Bird",
  "set": "ktk",
  "src": "https://media.wizards.com/images/magic/tcg/products/ktk/8arg43u984398yf/en_e5l3l6c42r.png",
  "colour": "w",
  "rarity": "c",
  "type": "Token Creature",
  "subtype": "Bird",
  "power": "3",
  "toughness": "4",
  "num": "001/013 T",
  "token": "true",
  "usableForDeckBuilding": false
 }
 ,{
  "title": "Spirit",
  "set": "ktk",
  "src": "https://media.wizards.com/images/magic/tcg/products/ktk/8arg43u984398yf/en_ivevzegdsc.png",
  "colour": "w",
  "rarity": "c",
  "type": "Token Creature",
  "subtype": "Spirit",
  "power": "1",
  "toughness": "1",
  "num": "002/013 T",
  "token": "true",
  "usableForDeckBuilding": false
 }
 ,{
  "title": "Warrior",
  "set": "ktk",
  "src": "https://media.wizards.com/images/magic/tcg/products/ktk/8arg43u984398yf/en_9uro1jblrh.png",
  "colour": "w",
  "rarity": "c",
  "type": "Token Creature",
  "subtype": "Warrior",
  "power": "1",
  "toughness": "1",
  "num": "003/013 T",
  "token": "true",
  "usableForDeckBuilding": false
 }
 ,{
  "title": "Warrior",
  "set": "ktk",
  "src": "https://media.wizards.com/images/magic/tcg/products/ktk/8arg43u984398yf/en_pfcpv8y40h.png",
  "colour": "w",
  "rarity": "c",
  "type": "Token Creature",
  "subtype": "Warrior",
  "power": "1",
  "toughness": "1",
  "num": "004/013 T",
  "token": "true",
  "usableForDeckBuilding": false
 }
 ,{
  "title": "Vampire",
  "set": "ktk",
  "src": "https://media.wizards.com/images/magic/tcg/products/ktk/8arg43u984398yf/en_yrqg0229z7.png",
  "colour": "b",
  "rarity": "c",
  "type": "Token Creature",
  "subtype": "Vampire",
  "power": "2",
  "toughness": "2",
  "num": "005/013 T",
  "token": "true",
  "usableForDeckBuilding": false
 }
 ,{
  "title": "Zombie",
  "set": "ktk",
  "src": "https://media.wizards.com/images/magic/tcg/products/ktk/8arg43u984398yf/en_6mdgfb0p61.png",
  "colour": "b",
  "rarity": "c",
  "type": "Token Creature",
  "subtype": "Zombie",
  "power": "2",
  "toughness": "2",
  "num": "006/013 T",
  "token": "true",
  "usableForDeckBuilding": false
 }
 ,{
  "title": "Goblin",
  "set": "ktk",
  "src": "https://media.wizards.com/images/magic/tcg/products/ktk/8arg43u984398yf/en_yf0eai89rz.png",
  "colour": "r",
  "rarity": "c",
  "type": "Token Creature",
  "subtype": "Goblin",
  "power": "1",
  "toughness": "1",
  "num": "007/013 T",
  "token": "true",
  "usableForDeckBuilding": false
 }
 ,{
  "title": "Bear",
  "set": "ktk",
  "src": "https://media.wizards.com/images/magic/tcg/products/ktk/8arg43u984398yf/en_1xtd9y36pp.png",
  "colour": "g",
  "rarity": "c",
  "type": "Token Creature",
  "subtype": "Bear",
  "power": "4",
  "toughness": "4",
  "num": "008/013 T",
  "token": "true",
  "usableForDeckBuilding": false
 }
 ,{
  "title": "Snake",
  "set": "ktk",
  "src": "https://media.wizards.com/images/magic/tcg/products/ktk/8arg43u984398yf/en_mv6rtsahnm.png",
  "colour": "g",
  "rarity": "c",
  "type": "Token Creature",
  "subtype": "Snake",
  "power": "1",
  "toughness": "1",
  "num": "009/013 T",
  "token": "true",
  "usableForDeckBuilding": false
 }
 ,{
  "title": "Spirit Warrior",
  "set": "ktk",
  "src": "https://media.wizards.com/images/magic/tcg/products/ktk/8arg43u984398yf/en_nelpmzkbvp.png",
  "colour": "m",
  "rarity": "c",
  "type": "Token Creature",
  "subtype": "Spirit Warrior",
  "power": "*",
  "toughness": "*",
  "num": "010/013 T",
  "token": "true",
  "usableForDeckBuilding": false
 }

 ,{
  "title": "Morph",
  "set": "ktk",
  "src": "https://media.wizards.com/images/magic/tcg/products/ktk/8arg43u984398yf/en_pu8esg2v7s.png",
  "colour": "o",
  "rarity": "c",
  "type": "Creature",
  "power": "2",
  "toughness": "2",
  "num": "011/013 T",
  "token": "true",
  "usableForDeckBuilding": false
 }

 ,{
  "title": "Emblem: Sarkhan",
  "set": "ktk",
  "src": "https://media.wizards.com/images/magic/tcg/products/ktk/8arg43u984398yf/en_08j1ajgxa1.png",
  "colour": "o",
  "rarity": "c",
  "type": "Emblem",
  "subtype": "Sarkhan",
  "num": "012/013 T",
  "token": "true",
  "usableForDeckBuilding": false
 }
 ,{
  "title": "Emblem: Sorin",
  "set": "ktk",
  "src": "https://media.wizards.com/images/magic/tcg/products/ktk/8arg43u984398yf/en_hnv6jpe4lr.png",
  "colour": "o",
  "rarity": "c",
  "type": "Emblem",
  "subtype": "Sorin",
  "num": "013/013 T",
  "token": "true",
  "usableForDeckBuilding": false
 }

]