[
  {
    "set": "thb",
    "src": "https://media.wizards.com/2019/thb/en_WOFcxR3XVQ.png",
    "num": "1/014 T",
    "colour": "w",
    "type": "Token Creature",
    "title": "Goat",
    "subtype": "Goat",
    "numInt": 1,
    "addedViaException": true,
    "mtgenId": "thb|1/014 T",
    "rarity": "c",
    "token": true,
    "usableForDeckBuilding": false
  },
  {
    "set": "thb",
    "src": "https://media.wizards.com/2019/thb/en_3gNoDkp9bM.png",
    "num": "10/014 T",
    "colour": "g",
    "type": "Token Creature",
    "title": "Spider",
    "subtype": "Spider",
    "numInt": 10,
    "addedViaException": true,
    "mtgenId": "thb|10/014 T",
    "rarity": "c",
    "token": true,
    "usableForDeckBuilding": false
  },
  {
    "set": "thb",
    "src": "https://media.wizards.com/2019/thb/en_ahsZMx1Bgw.png",
    "num": "11/014 T",
    "colour": "g",
    "type": "Token Creature",
    "title": "Wolf",
    "subtype": "Wolf",
    "numInt": 11,
    "addedViaException": true,
    "mtgenId": "thb|11/014 T",
    "rarity": "c",
    "token": true,
    "usableForDeckBuilding": false
  },
  {
    "set": "thb",
    "src": "https://media.wizards.com/2019/thb/en_2s5Hu4zIRB.png",
    "num": "12/014 T",
    "colour": "m",
    "type": "Token Creature",
    "title": "Nightmare",
    "subtype": "Nightmare",
    "numInt": 12,
    "addedViaException": true,
    "mtgenId": "thb|12/014 T",
    "rarity": "c",
    "token": true,
    "usableForDeckBuilding": false
  },
  {
    "set": "thb",
    "src": "https://media.wizards.com/2019/thb/en_JL3iie7Yl6.png",
    "num": "13/014 T",
    "colour": "c",
    "type": "Token Artifact",
    "title": "Gold",
    "subtype": "Gold",
    "numInt": 13,
    "addedViaException": true,
    "mtgenId": "thb|13/014 T",
    "rarity": "c",
    "token": true,
    "usableForDeckBuilding": false
  },
  {
    "set": "thb",
    "src": "https://media.wizards.com/2019/thb/en_aOl898FYE1.png",
    "num": "14/014 T",
    "colour": "c",
    "type": "Token Artifact Creature",
    "title": "Wall",
    "subtype": "Wall",
    "numInt": 14,
    "addedViaException": true,
    "mtgenId": "thb|14/014 T",
    "rarity": "c",
    "token": true,
    "usableForDeckBuilding": false
  },
  {
    "set": "thb",
    "src": "https://media.wizards.com/2019/thb/en_pssmp0NOLm.png",
    "num": "2/014 T",
    "colour": "w",
    "type": "Token Creature",
    "title": "Human Soldier",
    "subtype": "Human Soldier",
    "numInt": 2,
    "addedViaException": true,
    "mtgenId": "thb|2/014 T",
    "rarity": "c",
    "token": true,
    "usableForDeckBuilding": false
  },
  {
    "set": "thb",
    "src": "https://media.wizards.com/2019/thb/en_eARM9V2Cqr.png",
    "num": "3/014 T",
    "colour": "w",
    "type": "Token Creature",
    "title": "Pegasus",
    "subtype": "Pegasus",
    "numInt": 3,
    "addedViaException": true,
    "mtgenId": "thb|3/014 T",
    "rarity": "c",
    "token": true,
    "usableForDeckBuilding": false
  },
  {
    "set": "thb",
    "src": "https://media.wizards.com/2019/thb/en_e5USIcQfJ5.png",
    "num": "4/014 T",
    "colour": "u",
    "type": "Token Creature",
    "title": "Kraken",
    "subtype": "Kraken",
    "numInt": 4,
    "addedViaException": true,
    "mtgenId": "thb|4/014 T",
    "rarity": "c",
    "token": true,
    "usableForDeckBuilding": false
  },
  {
    "set": "thb",
    "src": "https://media.wizards.com/2019/thb/en_JVsG6IUqAl.png",
    "num": "5/014 T",
    "colour": "u",
    "type": "Token Creature",
    "title": "Reflection",
    "subtype": "Reflection",
    "numInt": 5,
    "addedViaException": true,
    "mtgenId": "thb|5/014 T",
    "rarity": "c",
    "token": true,
    "usableForDeckBuilding": false
  },
  {
    "set": "thb",
    "src": "https://media.wizards.com/2019/thb/en_rNRCyFa2mF.png",
    "num": "6/014 T",
    "colour": "u",
    "type": "Token Creature",
    "title": "Tentacle",
    "subtype": "Tentacle",
    "numInt": 6,
    "addedViaException": true,
    "mtgenId": "thb|6/014 T",
    "rarity": "c",
    "token": true,
    "usableForDeckBuilding": false
  },
  {
    "set": "thb",
    "src": "https://media.wizards.com/2019/thb/en_zh0TosPHeW.png",
    "num": "7/014 T",
    "colour": "b",
    "type": "Token Creature",
    "title": "Zombie",
    "subtype": "Zombie",
    "numInt": 7,
    "addedViaException": true,
    "mtgenId": "thb|7/014 T",
    "rarity": "c",
    "token": true,
    "usableForDeckBuilding": false
  },
  {
    "set": "thb",
    "src": "https://media.wizards.com/2019/thb/en_3b857qIBEs.png",
    "num": "8/014 T",
    "colour": "r",
    "type": "Token Creature",
    "title": "Elemental",
    "subtype": "Elemental",
    "numInt": 8,
    "addedViaException": true,
    "mtgenId": "thb|8/014 T",
    "rarity": "c",
    "token": true,
    "usableForDeckBuilding": false
  },
  {
    "set": "thb",
    "src": "https://media.wizards.com/2019/thb/en_u2PUCJEMfZ.png",
    "num": "9/014 T",
    "colour": "r",
    "type": "Token Creature",
    "title": "Satyr",
    "subtype": "Satyr",
    "numInt": 9,
    "addedViaException": true,
    "mtgenId": "thb|9/014 T",
    "rarity": "c",
    "token": true,
    "usableForDeckBuilding": false
  }
]