{
  "startProductName": "tsr-boosters",
  "packFiles": [
    "packs.json?v1.3"
  ],
  "cardFiles": [
    "cardsMain.json?v1.1",
    "cardsToken.json",
    "cardsTimeshifted.json?v1.1",
    "cardsPromo.json",
    "../cards/ads/cardsAds.json"
  ],
  "updates": [
    {
      "UpdateDate": "2021-07-03T23:30:00:00",
      "HtmlString": "Updated marketing cards to be more accurate for set, plus set chances as 1:3 token:marketing for core sets, 2:3 for expansions, and 9:1 as of Battle for Zendikar."
    },
    {
      "UpdateDate": "2021-03-08T13:30:00:00",
      "HtmlString": "Lotus Bloom foil now only a promo card, removed erroneous Vesuvus timeshifted placeholder, added promo card section."
    }
  ]
}