[
  {
    "set": "iko",
    "title": "Zilortha, Strength Incarnate",
    "src": "https://media.wizards.com/2020/iko/en_CoAEVWif9M.png",
    "cost": "3RG",
    "rarity": "m",
    "type": "Legendary Creature",
    "subtype": "Dinosaur",
    "power": "7",
    "toughness": "3",
    "colour": "m",
    "num": "275 P Buy-a-Box",
    "numInt": 275,
    "mtgenId": "iko|275 P Buy-a-Box",
    "includedReason": "Buy-a-Box Promo",
    "promo": true,
    "usableForDeckBuilding": false
  },
  {
    "src": "http://mtgen.net/cards/iko-prerelease-deck-box.png",
    "title": "Prerelease Deck Box",
    "colour": "o",
    "num": "006 Prerelease Deck Box",
    "rarity": "c",
    "type": "Insert",
    "includedReason": "Prerelease Promo",
    "addedViaException": true,
    "numInt": 6,
    "mtgenId": "iko|006 Prerelease Deck Box",
    "set": "iko",
    "promo": true,
    "usableForDeckBuilding": false
  },
  {
    "src": "http://mtgen.net/cards/mtg-deckbuilding-info.jpg",
    "src_large": "http://mtgen.net/cards/mtg-deckbuilding-info-lg.jpg",
    "height": 370,
    "width": 515,
    "title": "Deckbuilding Advice Insert",
    "colour": "o",
    "num": "007 Insert",
    "rarity": "c",
    "type": "Insert",
    "includedReason": "Prerelease Promo",
    "addedViaException": true,
    "numInt": 7,
    "mtgenId": "iko|007 Insert",
    "set": "iko",
    "promo": true,
    "usableForDeckBuilding": false
  },
  {
    "src": "http://mtgen.net/cards/mtg-spindown-life-counter-white.png",
    "title": "White Spindown Life Counter (Placeholder)",
    "colour": "o",
    "num": "001 Counter",
    "rarity": "c",
    "type": "Life Counter",
    "includedReason": "Prerelease Promo",
    "addedViaException": true,
    "numInt": 1,
    "mtgenId": "iko|001 Counter",
    "set": "iko",
    "promo": true,
    "usableForDeckBuilding": false
  },
  {
    "src": "http://mtgen.net/cards/mtg-spindown-life-counter-blue.png",
    "title": "Blue Spindown Life Counter (Placeholder)",
    "colour": "o",
    "num": "002 Counter",
    "rarity": "c",
    "type": "Life Counter",
    "includedReason": "Prerelease Promo",
    "addedViaException": true,
    "numInt": 2,
    "mtgenId": "iko|002 Counter",
    "set": "iko",
    "promo": true,
    "usableForDeckBuilding": false
  },
  {
    "src": "http://mtgen.net/cards/mtg-spindown-life-counter-black.png",
    "title": "Black Spindown Life Counter (Placeholder)",
    "colour": "o",
    "num": "003 Counter",
    "rarity": "c",
    "type": "Life Counter",
    "includedReason": "Prerelease Promo",
    "addedViaException": true,
    "numInt": 3,
    "mtgenId": "iko|003 Counter",
    "set": "iko",
    "promo": true,
    "usableForDeckBuilding": false
  },
  {
    "src": "http://mtgen.net/cards/mtg-spindown-life-counter-red.png",
    "title": "Red Spindown Life Counter (Placeholder)",
    "colour": "o",
    "num": "004 Counter",
    "rarity": "c",
    "type": "Life Counter",
    "includedReason": "Prerelease Promo",
    "addedViaException": true,
    "numInt": 4,
    "mtgenId": "iko|004 Counter",
    "set": "iko",
    "promo": true,
    "usableForDeckBuilding": false
  },
  {
    "src": "http://mtgen.net/cards/mtg-spindown-life-counter-green.png",
    "title": "Green Spindown Life Counter (Placeholder)",
    "colour": "o",
    "num": "005 Counter",
    "rarity": "c",
    "type": "Life Counter",
    "includedReason": "Prerelease Promo",
    "addedViaException": true,
    "numInt": 5,
    "mtgenId": "iko|005 Counter",
    "set": "iko",
    "promo": true,
    "usableForDeckBuilding": false
  }
]