[
 {
  "title": "Eldrazi Spawn",
  "set": "mm2",
  "src": "http://media.wizards.com/2015/mm2_9vgauji43t9a/en_ZEgJlqKKxe.png",
  "colour": "x",
  "rarity": "c",
  "type": "Token Creature",
  "subtype": "Eldrazi Spawn",
  "power": "0",
  "toughness": "1",
  "num": "001/016 T",
  "token": "true",
  "usableForDeckBuilding": false
 }
 ,{
  "title": "Eldrazi Spawn",
  "set": "mm2",
  "src": "http://media.wizards.com/2015/mm2_9vgauji43t9a/en_Hhuj1GUOBt.png",
  "colour": "x",
  "rarity": "c",
  "type": "Token Creature",
  "subtype": "Eldrazi Spawn",
  "power": "0",
  "toughness": "1",
  "num": "002/016 T",
  "token": "true",
  "usableForDeckBuilding": false
 }
 ,{
  "title": "Eldrazi Spawn",
  "set": "mm2",
  "src": "http://media.wizards.com/2015/mm2_9vgauji43t9a/en_fUx3VrMDnA.png",
  "colour": "x",
  "rarity": "c",
  "type": "Token Creature",
  "subtype": "Eldrazi Spawn",
  "power": "0",
  "toughness": "1",
  "num": "003/016 T",
  "token": "true",
  "usableForDeckBuilding": false
 }
 ,{
  "title": "Soldier",
  "set": "mm2",
  "src": "http://media.wizards.com/2015/mm2_9vgauji43t9a/en_vIxQpTbO6b.png",
  "colour": "w",
  "rarity": "c",
  "type": "Token Creature",
  "subtype": "Soldier",
  "power": "1",
  "toughness": "1",
  "num": "004/016 T",
  "token": "true",
  "usableForDeckBuilding": false
 }
 ,{
  "title": "Spirit",
  "set": "mm2",
  "src": "http://media.wizards.com/2015/mm2_9vgauji43t9a/en_E3hF5KOp1J.png",
  "colour": "b",
  "rarity": "c",
  "type": "Token Creature",
  "subtype": "Spirit",
  "power": "1",
  "toughness": "1",
  "num": "005/016 T",
  "token": "true",
  "usableForDeckBuilding": false
 }
 ,{
  "title": "Faerie Rogue",
  "set": "mm2",
  "src": "http://media.wizards.com/2015/mm2_9vgauji43t9a/en_6IOrNA1GbG.png",
  "colour": "b",
  "rarity": "c",
  "type": "Token Creature",
  "subtype": "Faerie Rogue",
  "power": "1",
  "toughness": "1",
  "num": "006/016 T",
  "token": "true",
  "usableForDeckBuilding": false
 }
 ,{
  "title": "Germ",
  "set": "mm2",
  "src": "http://media.wizards.com/2015/mm2_9vgauji43t9a/en_dKOkeEXQ9V.png",
  "colour": "b",
  "rarity": "c",
  "type": "Token Creature",
  "subtype": "Germ",
  "power": "0",
  "toughness": "0",
  "num": "007/016 T",
  "token": "true",
  "usableForDeckBuilding": false
 }
 ,{
  "title": "Thrull",
  "set": "mm2",
  "src": "http://media.wizards.com/2015/mm2_9vgauji43t9a/en_lDMIi3XONu.png",
  "colour": "b",
  "rarity": "c",
  "type": "Token Creature",
  "subtype": "Thrull",
  "power": "1",
  "toughness": "1",
  "num": "008/016 T",
  "token": "true",
  "usableForDeckBuilding": false
 }
 ,{
  "title": "Elephant",
  "set": "mm2",
  "src": "http://media.wizards.com/2015/mm2_9vgauji43t9a/en_tf0WqzqwuA.png",
  "colour": "g",
  "rarity": "c",
  "type": "Token Creature",
  "subtype": "Elephant",
  "power": "3",
  "toughness": "3",
  "num": "009/016 T",
  "token": "true",
  "usableForDeckBuilding": false
 }
 ,{
  "title": "Insect",
  "set": "mm2",
  "src": "http://media.wizards.com/2015/mm2_9vgauji43t9a/en_hqtAtsjDRA.png",
  "colour": "g",
  "rarity": "c",
  "type": "Token Creature",
  "subtype": "Insect",
  "power": "1",
  "toughness": "1",
  "num": "010/016 T",
  "token": "true",
  "usableForDeckBuilding": false
 }
 ,{
  "title": "Saproling",
  "set": "mm2",
  "src": "http://media.wizards.com/2015/mm2_9vgauji43t9a/en_hHD76MxLFo.png",
  "colour": "g",
  "rarity": "c",
  "type": "Token Creature",
  "subtype": "Saproling",
  "power": "1",
  "toughness": "1",
  "num": "011/016 T",
  "token": "true",
  "usableForDeckBuilding": false
 }
 ,{
  "title": "Snake",
  "set": "mm2",
  "src": "http://media.wizards.com/2015/mm2_9vgauji43t9a/en_0ZWDRrxtpY.png",
  "colour": "g",
  "rarity": "c",
  "type": "Token Creature",
  "subtype": "Snake",
  "power": "1",
  "toughness": "1",
  "num": "012/016 T",
  "token": "true",
  "usableForDeckBuilding": false
 }
 ,{
  "title": "Wolf",
  "set": "mm2",
  "src": "http://media.wizards.com/2015/mm2_9vgauji43t9a/en_Nd1vBcud86.png",
  "colour": "g",
  "rarity": "c",
  "type": "Token Creature",
  "subtype": "Wolf",
  "power": "2",
  "toughness": "2",
  "num": "013/016 T",
  "token": "true",
  "usableForDeckBuilding": false
 }
 ,{
  "title": "Worm",
  "set": "mm2",
  "src": "http://media.wizards.com/2015/mm2_9vgauji43t9a/en_o6daS1QNfK.png",
  "colour": "m",
  "rarity": "c",
  "type": "Token Creature",
  "subtype": "Worm",
  "power": "1",
  "toughness": "1",
  "num": "014/016 T",
  "token": "true",
  "usableForDeckBuilding": false
 }
 ,{
  "title": "Golem",
  "set": "mm2",
  "src": "http://media.wizards.com/2015/mm2_9vgauji43t9a/en_FFbEKgocU5.png",
  "colour": "a",
  "rarity": "c",
  "type": "Token Artifact Creature",
  "subtype": "Golem",
  "power": "3",
  "toughness": "3",
  "num": "015/016 T",
  "token": "true",
  "usableForDeckBuilding": false
 }
 ,{
  "title": "Myr",
  "set": "mm2",
  "src": "http://media.wizards.com/2015/mm2_9vgauji43t9a/en_ANw57RqESf.png",
  "colour": "a",
  "rarity": "c",
  "type": "Token Artifact Creature",
  "subtype": "Myr",
  "power": "1",
  "toughness": "1",
  "num": "016/016 T",
  "token": "true",
  "usableForDeckBuilding": false
 }

]